<command>
	<initRepository>
    </initRepository>
    <addVendor>	
	  	<name>Peter</name>
  		<note>Sale</note>
  		<website>google</website>
	</addVendor>
	<addCategory>
		<name>electric</name>
  		<note>cell phone</note>
	</addCategory>
    <addComp>	
	  	<name>C1</name>
  		<vendor>Peter</vendor>
  		<category>electric</category>
  		<constraints>
  			<cons1>n1</cons1>
  		 	<cons2>n2</cons2>
  		 	<cons3>n3</cons3>
  		</constraints>
	</addComp>
    <addTestSuite>
    	<suiteName>t1</suiteName>
    	<comName>C1</comName>
    </addTestSuite>
    <addTestSuite>
    	<suiteName>t2</suiteName>
    	<comName>C1</comName>
    </addTestSuite>
	<addTestSuite>
		<suiteName>t3</suiteName>
		<comName>C2</comName>
	</addTestSuite>
	<addTestSuite>
		<suiteName>t2</suiteName>
		<comName>C1</comName>
	</addTestSuite>
</command>  